dumbo_scopus/__init__.py
dumbo_scopus/__main__.py
dumbo_scopus/cli.py
dumbo_scopus/utils.py
dumbo_scopus-0.2.7.dist-info/LICENSE
dumbo_scopus-0.2.7.dist-info/WHEEL
dumbo_scopus-0.2.7.dist-info/METADATA
dumbo_scopus-0.2.7.dist-info/RECORD
