Metadata-Version: 2.1
Name: dumbo-scopus
Version: 0.2.7
Summary: Simple CLI to search on Scopus and obtain the results in a XLSX file
Author: Mario Alviano
Author-email: mario.alviano@gmail.com
Requires-Python: >=3.10,<4.0
Classifier: Programming Language :: Python :: 3
Classifier: Programming Language :: Python :: 3.10
Classifier: Programming Language :: Python :: 3.11
Requires-Dist: requests (>=2.28.2,<3.0.0)
Requires-Dist: rich (>=13.2.0,<14.0.0)
Requires-Dist: selenium (>=4.8.0,<5.0.0)
Requires-Dist: typer (>=0.7.0,<0.8.0)
